odoo/addons/website_event_excerpt_img/README.rst
odoo/addons/website_event_excerpt_img/__init__.py
odoo/addons/website_event_excerpt_img/__manifest__.py
odoo/addons/website_event_excerpt_img/i18n/es.po
odoo/addons/website_event_excerpt_img/models/__init__.py
odoo/addons/website_event_excerpt_img/models/event.py
odoo/addons/website_event_excerpt_img/static/description/backend.png
odoo/addons/website_event_excerpt_img/static/description/customize.png
odoo/addons/website_event_excerpt_img/static/description/frontend.png
odoo/addons/website_event_excerpt_img/static/description/icon.png
odoo/addons/website_event_excerpt_img/static/src/less/website_event_excerpt_img.less
odoo/addons/website_event_excerpt_img/views/assets.xml
odoo/addons/website_event_excerpt_img/views/event.xml
odoo/addons/website_event_excerpt_img/views/event_event_view.xml
odoo11_addon_website_event_excerpt_img-11.0.1.0.0.dist-info/METADATA
odoo11_addon_website_event_excerpt_img-11.0.1.0.0.dist-info/RECORD
odoo11_addon_website_event_excerpt_img-11.0.1.0.0.dist-info/WHEEL
odoo11_addon_website_event_excerpt_img-11.0.1.0.0.dist-info/top_level.txt
